<annotation>
	<folder>images</folder>
	<filename>fire2.jpg</filename>
	<path>C:\BplaFireMyProg\images\fire2.jpg</path>
	<source>
		<database>Unknown</database>
	</source>
	<size>
		<width>960</width>
		<height>639</height>
		<depth>3</depth>
	</size>
	<segmented>0</segmented>
	<object>
		<name>fire</name>
		<pose>Unspecified</pose>
		<truncated>1</truncated>
		<difficult>0</difficult>
		<bndbox>
			<xmin>1</xmin>
			<ymin>265</ymin>
			<xmax>99</xmax>
			<ymax>402</ymax>
		</bndbox>
	</object>
	<object>
		<name>fire</name>
		<pose>Unspecified</pose>
		<truncated>0</truncated>
		<difficult>0</difficult>
		<bndbox>
			<xmin>149</xmin>
			<ymin>226</ymin>
			<xmax>308</xmax>
			<ymax>282</ymax>
		</bndbox>
	</object>
	<object>
		<name>fire</name>
		<pose>Unspecified</pose>
		<truncated>0</truncated>
		<difficult>0</difficult>
		<bndbox>
			<xmin>338</xmin>
			<ymin>98</ymin>
			<xmax>958</xmax>
			<ymax>340</ymax>
		</bndbox>
	</object>
</annotation>
